invokeai_py_client/__init__.py
invokeai_py_client/client.py
invokeai_py_client/exceptions.py
invokeai_py_client/models.py
invokeai_py_client/board/__init__.py
invokeai_py_client/board/board_handle.py
invokeai_py_client/board/board_model.py
invokeai_py_client/board/board_repo.py
invokeai_py_client/dnn_model/__init__.py
invokeai_py_client/dnn_model/dnn_model_exceptions.py
invokeai_py_client/dnn_model/dnn_model_models.py
invokeai_py_client/dnn_model/dnn_model_repo.py
invokeai_py_client/dnn_model/dnn_model_types.py
invokeai_py_client/dnn_model/model_inst_job_handle.py
invokeai_py_client/ivk_fields/__init__.py
invokeai_py_client/ivk_fields/base.py
invokeai_py_client/ivk_fields/complex.py
invokeai_py_client/ivk_fields/conditioning.py
invokeai_py_client/ivk_fields/enums.py
invokeai_py_client/ivk_fields/model_conversion.py
invokeai_py_client/ivk_fields/models.py
invokeai_py_client/ivk_fields/primitives.py
invokeai_py_client/ivk_fields/resources.py
invokeai_py_client/queue/__init__.py
invokeai_py_client/queue/job_handle.py
invokeai_py_client/queue/queue_handle.py
invokeai_py_client/queue/queue_models.py
invokeai_py_client/queue/queue_repo.py
invokeai_py_client/quick/README.md
invokeai_py_client/quick/__init__.py
invokeai_py_client/quick/quick_client.py
invokeai_py_client/quick/prebuilt-workflows/README.md
invokeai_py_client/quick/prebuilt-workflows/copy-image.json
invokeai_py_client/quick/prebuilt-workflows/sdxl-text-to-image.json
invokeai_py_client/workflow/__init__.py
invokeai_py_client/workflow/field_plugins.py
invokeai_py_client/workflow/upstream_models.py
invokeai_py_client/workflow/workflow_handle.py
invokeai_py_client/workflow/workflow_model.py
invokeai_py_client/workflow/workflow_repo.py
invokeai_py_client-1.1.1.dist-info/METADATA
invokeai_py_client-1.1.1.dist-info/WHEEL
invokeai_py_client-1.1.1.dist-info/licenses/LICENSE
invokeai_py_client-1.1.1.dist-info/RECORD
