Metadata-Version: 2.4
Name: invokeai-py-client
Version: 1.1.1
Summary: A Python client library for interacting with InvokeAI APIs
Project-URL: Homepage, https://github.com/CodeGandee/invokeai-py-client
Project-URL: Repository, https://github.com/CodeGandee/invokeai-py-client
Project-URL: Documentation, https://codegandee.github.io/invokeai-py-client/
Project-URL: Issues, https://github.com/CodeGandee/invokeai-py-client/issues
Project-URL: Changelog, https://github.com/CodeGandee/invokeai-py-client/blob/main/docs/changelog.md
Project-URL: Discussions, https://github.com/CodeGandee/invokeai-py-client/discussions
Author-email: CodeGandee <igamenovoer@xx.com>
License: MIT License
License-File: LICENSE
Keywords: ai,api,client,flux,image-generation,invokeai,stable-diffusion
Classifier: Development Status :: 5 - Production/Stable
Classifier: Intended Audience :: Developers
Classifier: License :: OSI Approved :: MIT License
Classifier: Operating System :: MacOS
Classifier: Operating System :: Microsoft :: Windows
Classifier: Operating System :: OS Independent
Classifier: Operating System :: POSIX :: Linux
Classifier: Programming Language :: Python :: 3
Classifier: Programming Language :: Python :: 3.11
Classifier: Programming Language :: Python :: 3.12
Classifier: Programming Language :: Python :: 3.13
Classifier: Topic :: Internet :: WWW/HTTP :: Dynamic Content
Classifier: Topic :: Multimedia :: Graphics
Classifier: Topic :: Scientific/Engineering :: Artificial Intelligence
Classifier: Topic :: Software Development :: Libraries :: Python Modules
Classifier: Typing :: Typed
Requires-Python: >=3.11
Requires-Dist: aiohttp>=3.8.0
Requires-Dist: dynamicprompts>=0.31.0
Requires-Dist: imageio>=2.25.0
Requires-Dist: jsonpath-ng>=1.7.0
Requires-Dist: opencv-python>=4.5.0
Requires-Dist: pillow
Requires-Dist: pluggy>=1.0.0
Requires-Dist: pydantic>=2.5.0
Requires-Dist: python-socketio[asyncio-client]>=5.13.0
Requires-Dist: requests>=2.32.4
Requires-Dist: rich>=14.1.0
Requires-Dist: scipy>=1.16.1
Requires-Dist: tqdm>=4.67.1
Provides-Extra: dev
Requires-Dist: black>=23.0; extra == 'dev'
Requires-Dist: ipykernel>=6.30.1; extra == 'dev'
Requires-Dist: mypy>=1.0; extra == 'dev'
Requires-Dist: pre-commit>=3.0; extra == 'dev'
Requires-Dist: pytest-asyncio>=0.21; extra == 'dev'
Requires-Dist: pytest-cov>=4.0; extra == 'dev'
Requires-Dist: pytest>=7.0; extra == 'dev'
Requires-Dist: ruff>=0.1; extra == 'dev'
Provides-Extra: docs
Requires-Dist: mkdocs-material>=9.0; extra == 'docs'
Requires-Dist: mkdocs>=1.5; extra == 'docs'
Requires-Dist: mkdocstrings[python]>=0.20; extra == 'docs'
Provides-Extra: test
Requires-Dist: httpx>=0.25; extra == 'test'
Requires-Dist: pytest-asyncio>=0.21; extra == 'test'
Requires-Dist: pytest-cov>=4.0; extra == 'test'
Requires-Dist: pytest>=7.0; extra == 'test'
Requires-Dist: respx>=0.20; extra == 'test'
